plot_av/__init__.py
plot_av/av_plotter.py
plot_av/plot_av.py
plot_av/process_args.py
plot_av/stream_info.py
plot_av-0.1.4.dist-info/METADATA
plot_av-0.1.4.dist-info/WHEEL
plot_av-0.1.4.dist-info/entry_points.txt
plot_av-0.1.4.dist-info/licenses/LICENSE
plot_av-0.1.4.dist-info/RECORD
