Metadata-Version: 2.3
Name: plot_av
Version: 0.1.4
Summary: Plot Audio/Video streams for better insights
Project-URL: Homepage, https://github.com/wangyoucao577/plot-av
Project-URL: Issues, https://github.com/wangyoucao577/plot-av/issues
Author-email: Jay Zhang <wangyoucao577@gmail.com>
License:                                  Apache License
License-File: LICENSE
Classifier: Framework :: Matplotlib
Classifier: License :: OSI Approved :: Apache Software License
Classifier: Operating System :: OS Independent
Classifier: Programming Language :: Python :: 3
Requires-Python: >=3.8
Requires-Dist: av
Requires-Dist: matplotlib
